bigfix_prefetch/__init__.py
bigfix_prefetch/__main__.py
bigfix_prefetch/prefetch.py
bigfix_prefetch/prefetch_from_dictionary.py
bigfix_prefetch/prefetch_from_file.py
bigfix_prefetch/prefetch_from_url.py
bigfix_prefetch/prefetch_parse.py
bigfix_prefetch/prefetch_validate.py
bigfix_prefetch/prefetches_have_matching_hashes.py
bigfix_prefetch-1.1.5.dist-info/LICENSE
bigfix_prefetch-1.1.5.dist-info/METADATA
bigfix_prefetch-1.1.5.dist-info/WHEEL
bigfix_prefetch-1.1.5.dist-info/top_level.txt
bigfix_prefetch-1.1.5.dist-info/RECORD
