Metadata-Version: 2.1
Name: bigfix-prefetch
Version: 1.1.5
Summary: A python module for working with BigFix prefetches
Home-page: https://github.com/jgstew/bigfix_prefetch
Author: JGStew
Author-email: noreply@jgstew.com
Project-URL: Bug Tracker, https://github.com/jgstew/bigfix_prefetch/issues
Classifier: Programming Language :: Python :: 2
Classifier: Programming Language :: Python :: 3
Classifier: License :: OSI Approved :: MIT License
Classifier: Operating System :: OS Independent
Requires-Python: >=2.6
License-File: LICENSE
